src/Alu.sv
module alu (
    input [4:0] ALUControl,
    input [31:0] SrcA, 
    input [31:0] SrcB,

    output Zero,
    output reg [31:0] ALUResult
);

always_comb begin
    case (ALUControl)
        //Arithmetic
        4'b1000: ALUResult <= SrcA - SrcB;                                // Substraction
        4'b0000: ALUResult <= SrcA + SrcB;                                // Addition
        
        //Logic
        4'b0111: ALUResult <= SrcA & SrcB;                                // AND
        4'b0110: ALUResult <= SrcA | SrcB;                                // OR
        4'b0100: ALUResult <= SrcA ^ SrcB;                                // XOR
        //Compare
        4'b0010: ALUResult <= $signed(SrcA) < $signed(SrcB)? 1 : 0;       //SLT
        4'b0011: ALUResult <= $unsigned(SrcA) < $unsigned(SrcB)? 1 : 0;   //SLTU

        //Shift
        4'b0001: ALUResult <= SrcA << SrcB;                               //SLL
        4'b0101: ALUResult <= SrcA >> SrcB;                               //SRL
        4'b1101: ALUResult <= $signed(SrcA) >> SrcB;                      //SRA
    endcase
end

assign Zero = (ALUResult == 32'b0);

endmodule

unit_tests/ALU/testbench.sv
module testbench ();

reg clk;

initial begin
    $dumpfile("out.vcd");
    $dumpvars(0, testbench);
    
    clk = 0;
end

always begin
    #10 clk <= ~clk;
end

reg [3:0] ALUControl;
reg [31:0] SrcA, SrcB;
wire Zero;
wire [31:0] ALUResult;

alu test_alu( ALUControl, SrcA, SrcB, Zero, ALUResult);

reg [31:0]real_res;

reg correct;


initial begin

@(posedge clk);

    //ADD
    ALUControl = 4'b0000;
    
    SrcA = 32'b1;
    SrcB = 32'b1;
    real_res = SrcA + SrcB;
    #1

    correct = ALUResult == real_res;

    $display("%b | %d + %d = %d(%d)", correct, $signed(SrcA), $signed(SrcB), $signed(ALUResult), $signed(real_res));
    
@(posedge clk);    
    
    //SUB
    ALUControl = 4'b1000;
    
    SrcA = 3;
    SrcB = 1;
    real_res = SrcA - SrcB;
    #1

    correct = ALUResult == real_res;

    $display("%b | %d - %d = %d(%d)", correct, $signed(SrcA), $signed(SrcB), $signed(ALUResult), $signed(real_res));

@(posedge clk);    
    
    //AND
    ALUControl = 4'b0111;
    
    SrcA = 3;
    SrcB = 1;
    real_res = SrcA & SrcB;
    #1

    correct = ALUResult == real_res;

    $display("%b | %b & %b = %b(%b)", correct, $unsigned(SrcA), $unsigned(SrcB), $unsigned(ALUResult), $unsigned(real_res));
@(posedge clk);    
    
    //OR
    ALUControl = 4'b0110;
    
    SrcA = 3;
    SrcB = 1;
    real_res = SrcA | SrcB;
    #1

    correct = ALUResult == real_res;

    $display("%b | %b | %b = %b(%b)", correct, $unsigned(SrcA), $unsigned(SrcB), $unsigned(ALUResult), $unsigned(real_res));
@(posedge clk);    
    
    //XOR
    ALUControl = 4'b0100;
    
    SrcA = 3;
    SrcB = 1;
    real_res = SrcA ^ SrcB;
    #1

    correct = ALUResult == real_res;

    $display("%b | %b ^ %b = %b(%b)", correct, $unsigned(SrcA), $unsigned(SrcB), $unsigned(ALUResult), $unsigned(real_res));
@(posedge clk);    
    
    //SLT
    ALUControl = 4'b0010;
    
    SrcA = -3;
    SrcB = 1;
    real_res = $signed(SrcA) < $signed(SrcB);
    #1

    correct = ALUResult == real_res;

    $display("%b | %b < %b = %b(%b)", correct, $signed(SrcA), $signed(SrcB), $signed(ALUResult), $signed(real_res));

@(posedge clk);    
    
    //SLTU
    ALUControl = 4'b0011;
    
    SrcA = -3;
    SrcB = 1;
    real_res = $unsigned(SrcA) < $unsigned(SrcB);
    #1

    correct = ALUResult == real_res;

    $display("%b | %b < %b = %b(%b)", correct, $unsigned(SrcA), $unsigned(SrcB), $unsigned(ALUResult), $unsigned(real_res));

@(posedge clk);    
    
    //SLL
    ALUControl = 4'b0001;
    
    SrcA = -133;
    SrcB = 2;
    real_res = SrcA << SrcB;
    #1

    correct = ALUResult == real_res;

    $display("%b | %b << %d = %b(%b)", correct, $unsigned(SrcA), $unsigned(SrcB), $unsigned(ALUResult), $unsigned(real_res));

@(posedge clk);    
    
    //SRL
    ALUControl = 4'b0101;
    
    SrcA = -1000;
    SrcB = 2;
    real_res = SrcA >> SrcB;
    #1

    correct = ALUResult == real_res;

    $display("%b | %b >> %d = %b(%b)", correct, $unsigned(SrcA), $unsigned(SrcB), $unsigned(ALUResult), $unsigned(real_res));

@(posedge clk);    
    
    //SRA
    ALUControl = 4'b1101;
    
    SrcA = -1000;
    SrcB = 3;
    real_res = $signed(SrcA) >> SrcB;
    #1

    correct = ALUResult == real_res;

    $display("%b | %b >> %d = %b(%b)", correct, $unsigned(SrcA), $unsigned(SrcB), $unsigned(ALUResult), $unsigned(real_res));

@(posedge clk);    
    $finish;

end

endmodule

unit_tests/ALU/out.vcd
$date
	Thu Feb 22 12:11:39 2024
$end
$version
	Icarus Verilog
$end
$timescale
	1s
$end
$scope module testbench $end
$var wire 1 ! Zero $end
$var wire 32 " ALUResult [31:0] $end
$var reg 4 # ALUControl [3:0] $end
$var reg 32 $ SrcA [31:0] $end
$var reg 32 % SrcB [31:0] $end
$var reg 1 & clk $end
$var reg 1 ' correct $end
$var reg 32 ( real_res [31:0] $end
$scope module test_alu $end
$var wire 5 ) ALUControl [4:0] $end
$var wire 32 * SrcA [31:0] $end
$var wire 32 + SrcB [31:0] $end
$var wire 1 ! Zero $end
$var reg 32 , ALUResult [31:0] $end
$upscope $end
$upscope $end
$enddefinitions $end
$comment Show the parameter values. $end
$dumpall
$end
#0
$dumpvars
bx ,
bx +
bx *
b0xxxx )
bx (
x'
0&
bx %
bx $
bx #
bx "
x!
$end
#10
0!
b10 "
b10 ,
b0 )
b10 (
b1 %
b1 +
b1 $
b1 *
b0 #
1&
#11
1'
#20
0&
#30
b1000 )
b11 $
b11 *
b1000 #
1&
#40
0&
#50
b1 "
b1 ,
b111 )
b1 (
b111 #
1&
#60
0&
#70
b11 "
b11 ,
b110 )
b11 (
b110 #
1&
#80
0&
#90
b10 "
b10 ,
b100 )
b10 (
b100 #
1&
#100
0&
#110
b1 "
b1 ,
b10 )
b1 (
b11111111111111111111111111111101 $
b11111111111111111111111111111101 *
b10 #
1&
#120
0&
#130
1!
b0 "
b0 ,
b11 )
b0 (
b11 #
1&
#140
0&
#150
0!
b11111111111111111111110111101100 "
b11111111111111111111110111101100 ,
b1 )
b11111111111111111111110111101100 (
b10 %
b10 +
b11111111111111111111111101111011 $
b11111111111111111111111101111011 *
b1 #
1&
#160
0&
#170
b111111111111111111111100000110 "
b111111111111111111111100000110 ,
b101 )
b111111111111111111111100000110 (
b11111111111111111111110000011000 $
b11111111111111111111110000011000 *
b101 #
1&
#180
0&
#190
b11111111111111111111110000011 "
b11111111111111111111110000011 ,
b1101 )
b11111111111111111111110000011 (
b11 %
b11 +
b1101 #
1&
